setup.py
clap/__init__.py
clap/builder.py
clap/checker.py
clap/errors.py
clap/formatter.py
clap/helper.py
clap/mode.py
clap/option.py
clap/parser.py
clap/shared.py
clap_api.egg-info/PKG-INFO
clap_api.egg-info/SOURCES.txt
clap_api.egg-info/dependency_links.txt
clap_api.egg-info/top_level.txt