Metadata-Version: 1.1
Name: clap-api
Version: 0.10.1
Summary: Command Line Arguments Parser
Home-page: https://github.com/marekjm/clap
Author: Marek Marecki
Author-email: marekjm@ozro.pw
License: GNU GPL v3
Keywords: commandline arguments parser cli library
Platform: UNKNOWN
Classifier: Development Status :: 4 - Beta
Classifier: Intended Audience :: Developers
Classifier: License :: OSI Approved :: GNU General Public License v3 (GPLv3)
Classifier: Programming Language :: Python :: 3 :: Only
Classifier: Programming Language :: Python :: Implementation :: CPython
Classifier: Topic :: Software Development :: Libraries
Classifier: Topic :: Software Development :: Libraries :: Python Modules
Classifier: Topic :: Utilities
